aws_lambda/__init__.py
aws_lambda/_version.py
aws_lambda/aws_lambda.py
tests/__init__.py
tests/test_aws_lambda.py
tests/package/__init__.py
tests/package/example_package.py
tests/test_lambdas/__init__.py
tests/test_lambdas/example_function.py
tests/test_lambdas/example_function_update.py
tests/test_lambdas/function_with_package.py
tests/test_lambdas/function_with_req_pack.py
tests/test_lambdas/function_with_requirements.py
tests/test_lambdas/requirements.txt
python_lambda_4dn-1.0.1.dist-info/LICENSE
python_lambda_4dn-1.0.1.dist-info/METADATA
python_lambda_4dn-1.0.1.dist-info/WHEEL
python_lambda_4dn-1.0.1.dist-info/top_level.txt
python_lambda_4dn-1.0.1.dist-info/RECORD
