Metadata-Version: 2.1
Name: python-lambda-4dn
Version: 1.0.1
Summary: FORKED for 4dn-dcic. Use to package and deploy lambda functions.
Home-page: https://github.com/4dn-dcic/python-lambda
Author: 4DN Team at Harvard Medical School
Author-email: william_ronchetti@hms.harvard.edu
License: ISCL
Keywords: python-lambda
Platform: UNKNOWN
Classifier: Development Status :: 4 - Beta
Classifier: Intended Audience :: Developers
Classifier: License :: OSI Approved :: MIT License
Classifier: Natural Language :: English
Classifier: Programming Language :: Python :: 3.6
Requires-Dist: botocore (==1.13.7)
Requires-Dist: boto3 (==1.10.7)
Requires-Dist: docutils (>=0.14)
Requires-Dist: six (==1.12.0)
